{
  "name": "콜롬비아 후일라 EA 디카페인",
  "origin": "콜롬비아 (Colombia)",
  "region": "후일라 (Huila)",
  "farm": "후일라 지역 소농 연합 (Huila Smallholders)",
  "altitude": "1,200m - 1,800m",
  "variety": "카스티요, 콜롬비아, 카투라 (Castillo, Colombia, Caturra)",
  "process": "에틸 아세테이트(EA) 디카페인 (Sugar Cane Process)",
  "cup_notes": "밀크 초콜릿, 구운 견과류, 갈색 설탕의 단맛, 은은한 사과 산미, 클린 컵",
  "awards": [
    "해당 사항 없음 (디카페인 공정 특성상 일반 CoE 출품은 제한적이나, 고품질 스페셜티 베이스 사용)"
  ],
  "price_range_krw": "18,000원 - 24,000원",
  "market_grade": "스페셜티",
  "overview": [
    "사탕수수 유래 성분을 활용한 친환경 EA 공법으로 커피 본연의 향미 손실 최소화",
    "콜롬비아 후일라 지역 특유의 밸런스 좋은 단맛과 부드러운 바디감이 특징",
    "화학적 잔여물 걱정 없는 안전한 공정으로 디카페인 특유의 이취가 적고 깔끔함"
  ],
  "farm_info": "콜롬비아 남서부의 후일라(Huila) 지역은 화산재 토양과 적절한 일조량, 강수량을 갖춘 천혜의 커피 생산지입니다. 본 생두는 후일라 지역의 엄선된 스페셜티급 생두를 수확하여, 인근의 디카페인 공장(Descafecol 등)으로 이송해 사탕수수를 발효시켜 얻은 천연 에틸 아세테이트를 활용해 카페인을 제거했습니다.",
  "harvest_season": "9월 - 1월 (Main Crop) / 4월 - 6월 (Mitaca Crop)",
  "grade": "Excelso / Supremo",
  "price_factors": "천연 용매를 사용하는 EA 공정의 추가 비용 발생, 일반 커머셜 디카페인 대비 높은 생두 베이스 품질, 국제 물류비 및 환율 변동성",
  "distributor": "코빈즈커피",
  "price": 21300,
  "date": "2026-01-10"
}